entry_point_inspector/__init__.py
entry_point_inspector/app.py
entry_point_inspector/ep.py
entry_point_inspector/group.py
entry_point_inspector-0.2.2.dist-info/METADATA
entry_point_inspector-0.2.2.dist-info/WHEEL
entry_point_inspector-0.2.2.dist-info/entry_points.txt
entry_point_inspector-0.2.2.dist-info/licenses/LICENSE
entry_point_inspector-0.2.2.dist-info/RECORD
