Metadata-Version: 2.4
Name: entry_point_inspector
Version: 0.2.2
Summary: Tool for looking at the entry point plugins on a system
Project-URL: Homepage, https://github.com/dhellmann/entry_point_inspector
Author-email: Doug Hellmann <doug@doughellmann.com>
License: ASL 2.0
License-File: LICENSE
Classifier: Development Status :: 4 - Beta
Classifier: Environment :: Console
Classifier: Intended Audience :: Developers
Classifier: License :: OSI Approved :: Apache Software License
Classifier: Programming Language :: Python
Classifier: Programming Language :: Python :: 3
Classifier: Programming Language :: Python :: 3.11
Classifier: Programming Language :: Python :: 3.12
Classifier: Programming Language :: Python :: 3.13
Requires-Python: >=3.11
Requires-Dist: cliff
Requires-Dist: setuptools
